test/__init__.py
test/integration/__init__.py
test/integration/test_AdfsCheckpoint.py
test/integration/test_AdfsIngestor.py
test/integration/test_AdfsStreamWriter.py
test/integration/test_AwsS3Checkpoint.py
test/integration/test_AwsS3Ingestor.py
test/integration/test_AwsS3StreamWriter.py
test/integration/test_FileCheckpoint.py
test/integration/test_FtpIngestor.py
test/integration/test_HttpIngestor.py
test/integration/test_PaginatedHttpIngestor.py
test/unit/__init__.py
test/unit/test_FileIngestor.py
test/unit/test_FileStreamWriter.py
test/unit/test_HttpIngestor.py
test/unit/test_PaginatedHttpIngestor.py
test/unit/test_StringIngestor.py
test/unit/test_batch.py
xcputils/__init__.py
xcputils/batch.py
xcputils/checkpoints/__init__.py
xcputils/checkpoints/aws.py
xcputils/checkpoints/az.py
xcputils/checkpoints/file.py
xcputils/ingestion/__init__.py
xcputils/ingestion/aws.py
xcputils/ingestion/az.py
xcputils/ingestion/file.py
xcputils/ingestion/ftp.py
xcputils/ingestion/http.py
xcputils/ingestion/string.py
xcputils/streaming/__init__.py
xcputils/streaming/aws.py
xcputils/streaming/az.py
xcputils/streaming/file.py
xcputils/streaming/string.py
xcputils-0.0.1.dist-info/LICENSE
xcputils-0.0.1.dist-info/METADATA
xcputils-0.0.1.dist-info/WHEEL
xcputils-0.0.1.dist-info/top_level.txt
xcputils-0.0.1.dist-info/RECORD
