Metadata-Version: 2.1
Name: xcputils
Version: 0.0.1
Summary: Utilities for copying data
Home-page: https://github.com/henrikbulldog/xcputils
Author: Henrik Thomsen
Author-email: henrik.thomsen.dk@gmail.dk
Project-URL: Bug Tracker, https://github.com/henrikbulldog/xcputils/issues
Classifier: Programming Language :: Python :: 3
Classifier: License :: OSI Approved :: The Unlicense (Unlicense)
Classifier: Operating System :: OS Independent
Requires-Python: >=3.8
License-File: LICENSE
Requires-Dist: nest-asyncio
Requires-Dist: requests
Requires-Dist: boto3
Requires-Dist: azure-storage-file-datalake
Requires-Dist: azure-identity
